motifqu/__init__.py
motifqu/__main__.py
motifqu/bio_patterns.py
motifqu/cli.py
motifqu/discovery.py
motifqu/fasta.py
motifqu/grover.py
motifqu/util.py
motifqu/visualization.py
motifqu-1.0.1.dist-info/licenses/LICENSE
motifqu-1.0.1.dist-info/METADATA
motifqu-1.0.1.dist-info/WHEEL
motifqu-1.0.1.dist-info/entry_points.txt
motifqu-1.0.1.dist-info/top_level.txt
motifqu-1.0.1.dist-info/RECORD
