Metadata-Version: 2.4
Name: MotifQu
Version: 1.0.1
Summary: Quantum motif search and discovery using Grover's algorithm over genomic FASTA sequences.
Author-email: Akshay Uttarkar <akshayuttarkar@gmail.com>, Vidya Niranjan <vidya.n@mitvpu.ac.in>
License: MIT
Keywords: bioinformatics,motif,grover,qiskit,quantum,discovery,k-mer
Classifier: Intended Audience :: Science/Research
Classifier: License :: OSI Approved :: MIT License
Classifier: Programming Language :: Python :: 3
Classifier: Programming Language :: Python :: 3 :: Only
Classifier: Topic :: Scientific/Engineering :: Bio-Informatics
Classifier: Topic :: Scientific/Engineering :: Physics
Requires-Python: >=3.9
License-File: LICENSE
Requires-Dist: numpy>=1.23
Requires-Dist: qiskit>=1.0
Requires-Dist: qiskit-aer>=0.13
Requires-Dist: matplotlib>=3.5
Requires-Dist: pylatexenc>=2.10
Provides-Extra: dev
Requires-Dist: build>=1.0.0; extra == "dev"
Requires-Dist: twine>=5.0.0; extra == "dev"
Requires-Dist: pytest>=7.0.0; extra == "dev"
Requires-Dist: ruff>=0.5.0; extra == "dev"
Dynamic: license-file
